ezntfs/__init__.py
ezntfs/app.py
ezntfs/cli.py
ezntfs/ezntfs.py
ezntfs-1.1.4.dist-info/entry_points.txt
ezntfs-1.1.4.dist-info/LICENSE
ezntfs-1.1.4.dist-info/WHEEL
ezntfs-1.1.4.dist-info/METADATA
ezntfs-1.1.4.dist-info/RECORD
