Metadata-Version: 2.1
Name: ezntfs
Version: 1.1.4
Summary: An easy-to-use wrapper for NTFS-3G on macOS.
Author-email: Matt <lezgomatt@gmail.com>
Requires-Python: >=3.6
Classifier: Environment :: Console
Classifier: License :: OSI Approved :: zlib/libpng License
Classifier: Operating System :: MacOS :: MacOS X
Classifier: Programming Language :: Python
Classifier: Programming Language :: Python :: 3
Classifier: Programming Language :: Python :: 3 :: Only
Classifier: Topic :: System :: Filesystems
Classifier: Topic :: Utilities
Requires-Dist: pyobjc
Project-URL: Source, https://github.com/lezgomatt/ezntfs
